README.rst
setup.py
askstack/__init__.py
askstack/askstack.py
askstack.egg-info/PKG-INFO
askstack.egg-info/SOURCES.txt
askstack.egg-info/dependency_links.txt
askstack.egg-info/entry_points.txt
askstack.egg-info/requires.txt
askstack.egg-info/top_level.txt