Metadata-Version: 1.0
Name: askstack
Version: 0.1.3
Summary: Search answers on stackoverflow
Home-page: https://github.com/pdrb/askstack
Author: Pedro Buteri Gonring
Author-email: pedro@bigode.net
License: MIT
Keywords: search answer ask stack overflow command line
Platform: UNKNOWN
